fpga_files/rtl/compute/mac.v
// MAC implementation block

module mac #(
    parameter ACC_WIDTH = 24,
    parameter D_WIDTH = 8
)
(
    input clk,
    input valid, // Enable compute
    input clear, // Clear values
    input [D_WIDTH -1:0] A,
    input [D_WIDTH-1:0] B,

    output [ACC_WIDTH-1:0] acc_out
);

    // If clear and valid on same cycle, only A*B accumulated
    // If clear and no valid, acc cleared
    // If only valid, then A*B added to accumulator

    wire[(D_WIDTH*2)-1:0] mult;
    wire[ACC_WIDTH -1 : 0] mult_extended;
    wire[ACC_WIDTH-1:0] acc_next;

    reg [ACC_WIDTH-1:0] acc = {ACC_WIDTH{1'b0}};


    assign mult = A * B; // Multiply
    assign mult_extended = {{(ACC_WIDTH - (2*D_WIDTH)){1'b0}}, mult};
    assign acc_next = clear ? mult_extended : mult_extended + acc; // Add


    always @(posedge clk) begin
        if(valid) begin
            acc <= acc_next; // Assign to next if valid
        end else if (clear) begin
            acc <= {ACC_WIDTH{1'b0}}; // Clear if only clear
        end
    end

    assign acc_out = acc;

endmodule

fpga_files/rtl/compute/matrix_mult_datapath.v
module mult_datapath #(
    parameter D_WIDTH = 8,
    parameter ACC_WIDTH = 24
)(
    input clk,

    // Control signals
    input load_values,
    input select_k,
    input enable,
    input clear,
    input load_outputs,

    // Data inputs
    input  [D_WIDTH-1:0] a00, a01, a10, a11,
    input  [D_WIDTH-1:0] b00, b01, b10, b11,

    // Data outputs
    output reg [ACC_WIDTH-1:0] c00, c01, c10, c11
);

    reg [D_WIDTH-1:0] a00_l, a01_l, a10_l, a11_l;
    reg [D_WIDTH-1:0] b00_l, b01_l, b10_l, b11_l;


    // MAC CONTROL SIGNALS
    wire [3:0] mac_valid;
    wire [3:0] mac_load;
    wire [3:0] mac_clear;
    reg [3:0][D_WIDTH-1:0] mac_a;
    reg [3:0][D_WIDTH-1:0] mac_b;
    wire [ACC_WIDTH-1:0] mac_c00, mac_c01, mac_c10, mac_c11;


    always @(posedge clk) begin
        if(load_values) begin
            {a00_l, a01_l, a10_l, a11_l} <= {a00, a01, a10, a11};
            {b00_l, b01_l, b10_l, b11_l} <= {b00, b01, b10, b11};
        end else if (load_outputs) begin
            {c00, c01, c10, c11} <= {mac_c00, mac_c01, mac_c10, mac_c11};
        end
    end

    assign mac_valid = {4{enable}};
    assign mac_clear = {4{clear}};

    always @(*) begin
        if(enable & ~select_k) begin
            mac_a[0] = a00_l;
            mac_b[0] = b00_l;
            mac_a[1] = a00_l;
            mac_b[1] = b01_l;
            mac_a[2] = a10_l;
            mac_b[2] = b00_l;
            mac_a[3] = a10_l;
            mac_b[3] = b01_l;
        end else if(enable) begin
            mac_a[0] = a01_l;
            mac_b[0] = b10_l;
            mac_a[1] = a01_l;
            mac_b[1] = b11_l;
            mac_a[2] = a11_l;
            mac_b[2] = b10_l;
            mac_a[3] = a11_l;
            mac_b[3] = b11_l;
        end else begin
            mac_a = 'd0;
            mac_b = 'd0;
        end
    end

    mac #(
        .ACC_WIDTH(ACC_WIDTH),
        .D_WIDTH(D_WIDTH)
    ) mac_u_0 (
        .clk     (clk),
        .valid   (mac_valid[0]),
        .clear   (mac_clear[0]),
        .A       (mac_a[0]),
        .B       (mac_b[0]),
        .acc_out (mac_c00)
    );

    mac #(
        .ACC_WIDTH(ACC_WIDTH),
        .D_WIDTH(D_WIDTH)
    ) mac_u_1 (
        .clk     (clk),
        .valid   (mac_valid[1]),
        .clear   (mac_clear[1]),
        .A       (mac_a[1]),
        .B       (mac_b[1]),
        .acc_out (mac_c01)
    );

    mac #(
        .ACC_WIDTH(ACC_WIDTH),
        .D_WIDTH(D_WIDTH)
    ) mac_u_2 (
        .clk     (clk),
        .valid   (mac_valid[2]),
        .clear   (mac_clear[2]),
        .A       (mac_a[2]),
        .B       (mac_b[2]),
        .acc_out (mac_c10)
    );

    mac #(
        .ACC_WIDTH(ACC_WIDTH),
        .D_WIDTH(D_WIDTH)
    ) mac_u_3 (
        .clk     (clk),
        .valid   (mac_valid[3]),
        .clear   (mac_clear[3]),
        .A       (mac_a[3]),
        .B       (mac_b[3]),
        .acc_out (mac_c11)
    );



endmodule

fpga_files/rtl/compute/matrix_mult_controller.v
module matrix_mult_controller (
    input clk,
    input req_valid,

    // Control signals to datapath
    output reg load_values,
    output reg select_k,
    output reg enable,
    output reg clear,
    output reg load_outputs,

    output reg done
);

    // FSM state encoding
    parameter [2:0] IDLE = 3'd0,
                     LOAD = 3'd1,
                     K1   = 3'd2,
                     K2   = 3'd3,
                     SAVE = 3'd4;

    reg [2:0] current_state = IDLE;
    reg [2:0] next_state;

    // State register
    always @(posedge clk) begin
        current_state <= next_state;
    end

    // Next-state logic
    always @(*) begin
        next_state = current_state;

        case (current_state)
            IDLE: begin
                if(req_valid) begin
                    next_state = LOAD;
                end else begin
                    next_state = IDLE;
                end
            end

            LOAD: begin
                next_state = K1;
            end

            K1: begin
                next_state = K2;
            end

            K2: begin
                next_state = SAVE;
            end

            SAVE: begin
                next_state = IDLE;
            end

            default: begin
                next_state = IDLE;
            end
        endcase
    end

    // Output logic
    always @(*) begin
        load_values  = 1'b0;
        select_k     = 1'b0;
        enable       = 1'b0;
        clear        = 1'b0;
        load_outputs = 1'b0;
        done         = 1'b0;

        case (current_state)
            IDLE: begin
                done = 1'b1;
            end

            LOAD: begin
                clear = 1'b1;
                load_values = 1'b1;
            end

            K1: begin
                enable = 1'b1;
                select_k = 1'b0;
            end

            K2: begin
                enable = 1'b1;
                select_k = 1'b1;
            end

            SAVE: begin
                load_outputs = 1'b1;
            end

            default: begin
                done = 1'b1;
            end
        endcase
    end

endmodule

fpga_files/rtl/compute/matrix_mult_top.v
module matrix_mult_top #(
    parameter D_WIDTH = 4,
    parameter ACC_WIDTH = 16
)(
    input clk,
    input req_valid,
    output done,

    // Matrix A / B inputs
    input  [D_WIDTH-1:0] a00, a01, a10, a11,
    input  [D_WIDTH-1:0] b00, b01, b10, b11,

    // Matrix C output
    output [ACC_WIDTH-1:0] c00, c01, c10, c11
);

    // Controller -> datapath control signals
    wire load_values;
    wire select_k;
    wire enable;
    wire clear;
    wire load_outputs;

    matrix_mult_controller u_controller (
        .clk          (clk),
        .req_valid    (req_valid),
        .load_values  (load_values),
        .select_k     (select_k),
        .enable       (enable),
        .clear        (clear),
        .load_outputs (load_outputs),
        .done         (done)
    );

    mult_datapath #(
        .D_WIDTH   (D_WIDTH),
        .ACC_WIDTH (ACC_WIDTH)
    ) u_datapath (
        .clk          (clk),
        .load_values  (load_values),
        .select_k     (select_k),
        .enable       (enable),
        .clear        (clear),
        .load_outputs (load_outputs),
        .a00 (a00), .a01 (a01), .a10 (a10), .a11 (a11),
        .b00 (b00), .b01 (b01), .b10 (b10), .b11 (b11),
        .c00 (c00), .c01 (c01), .c10 (c10), .c11 (c11)
    );

endmodule

fpga_files/tb/matrix_mult/tb_matrix_mult.v
`timescale 1ns/1ps

module tb_matrix_mult_top;

    parameter D_WIDTH = 4;
    parameter ACC_WIDTH = 16;
    parameter CLK_PERIOD = 10;

    // DUT inputs
    reg clk;
    reg req_valid;
    reg [D_WIDTH-1:0] a00, a01, a10, a11;
    reg [D_WIDTH-1:0] b00, b01, b10, b11;

    // DUT outputs
    wire done;
    wire [ACC_WIDTH-1:0] c00, c01, c10, c11;

    matrix_mult_top #(
        .D_WIDTH   (D_WIDTH),
        .ACC_WIDTH (ACC_WIDTH)
    ) uut (
        .clk       (clk),
        .req_valid (req_valid),
        .done      (done),
        .a00 (a00), .a01 (a01), .a10 (a10), .a11 (a11),
        .b00 (b00), .b01 (b01), .b10 (b10), .b11 (b11),
        .c00 (c00), .c01 (c01), .c10 (c10), .c11 (c11)
    );

    // Free-running system clock
    initial begin
        clk = 1'b0;
        forever #(CLK_PERIOD/2) clk = ~clk;
    end

    // Stimulus: 2x2 matrix multiply
    //   A = [1 2; 3 4]   B = [5 6; 7 8]
    //   Expected C = A*B = [19 22; 43 50]
    initial begin
        req_valid <= 1'b0;
        a00 <= 4'd1; a01 <= 4'd2; a10 <= 4'd3; a11 <= 4'd4;
        b00 <= 4'd5; b01 <= 4'd6; b10 <= 4'd7; b11 <= 4'd8;

        repeat (3) @(posedge clk);

        // Assert req_valid to kick off the FSM
        @(negedge clk);
        req_valid <= 1'b1;

        @(negedge clk);
        req_valid <= 1'b0;

        // Wait for the datapath to go busy, then wait until it's done
        wait (done == 1'b0);
        $display("[%0t] Compute started, done deasserted.", $time);

        wait (done == 1'b1);
        $display("[%0t] Compute finished.", $time);
        $display("[%0t] c00=%0d c01=%0d c10=%0d c11=%0d", $time, c00, c01, c10, c11);

        if (c00 !== 16'd19 || c01 !== 16'd22 || c10 !== 16'd43 || c11 !== 16'd50) begin
            $display("[%0t] MISMATCH: expected c00=19 c01=22 c10=43 c11=50", $time);
        end else begin
            $display("[%0t] PASS: matrix multiply result matches expected values", $time);
        end

        repeat (10) @(posedge clk);
        $display("[%0t] All stimulus sent.", $time);
        $finish;
    end

endmodule

fpga_files/waves/tb_matrix_mult.vcd
$version Generated by VerilatedVcd $end
$timescale 1ps $end
 $scope module TOP $end
  $scope module tb_matrix_mult_top $end
   $var wire 32 Z D_WIDTH [31:0] $end
   $var wire 32 [ ACC_WIDTH [31:0] $end
   $var wire 32 \ CLK_PERIOD [31:0] $end
   $var wire 1 W clk $end
   $var wire 1 X req_valid $end
   $var wire 4 O a00 [3:0] $end
   $var wire 4 P a01 [3:0] $end
   $var wire 4 Q a10 [3:0] $end
   $var wire 4 R a11 [3:0] $end
   $var wire 4 S b00 [3:0] $end
   $var wire 4 T b01 [3:0] $end
   $var wire 4 U b10 [3:0] $end
   $var wire 4 V b11 [3:0] $end
   $var wire 1 + done $end
   $var wire 16 , c00 [15:0] $end
   $var wire 16 - c01 [15:0] $end
   $var wire 16 . c10 [15:0] $end
   $var wire 16 / c11 [15:0] $end
   $scope module uut $end
    $var wire 32 Z D_WIDTH [31:0] $end
    $var wire 32 [ ACC_WIDTH [31:0] $end
    $var wire 1 W clk $end
    $var wire 1 X req_valid $end
    $var wire 1 + done $end
    $var wire 4 O a00 [3:0] $end
    $var wire 4 P a01 [3:0] $end
    $var wire 4 Q a10 [3:0] $end
    $var wire 4 R a11 [3:0] $end
    $var wire 4 S b00 [3:0] $end
    $var wire 4 T b01 [3:0] $end
    $var wire 4 U b10 [3:0] $end
    $var wire 4 V b11 [3:0] $end
    $var wire 16 , c00 [15:0] $end
    $var wire 16 - c01 [15:0] $end
    $var wire 16 . c10 [15:0] $end
    $var wire 16 / c11 [15:0] $end
    $var wire 1 0 load_values $end
    $var wire 1 1 select_k $end
    $var wire 1 2 enable $end
    $var wire 1 3 clear $end
    $var wire 1 4 load_outputs $end
    $scope module u_controller $end
     $var wire 1 W clk $end
     $var wire 1 X req_valid $end
     $var wire 1 0 load_values $end
     $var wire 1 1 select_k $end
     $var wire 1 2 enable $end
     $var wire 1 3 clear $end
     $var wire 1 4 load_outputs $end
     $var wire 1 + done $end
     $var wire 3 ] IDLE [2:0] $end
     $var wire 3 ^ LOAD [2:0] $end
     $var wire 3 _ K1 [2:0] $end
     $var wire 3 ` K2 [2:0] $end
     $var wire 3 a SAVE [2:0] $end
     $var wire 3 " current_state [2:0] $end
     $var wire 3 Y next_state [2:0] $end
    $upscope $end
    $scope module u_datapath $end
     $var wire 32 Z D_WIDTH [31:0] $end
     $var wire 32 [ ACC_WIDTH [31:0] $end
     $var wire 1 W clk $end
     $var wire 1 0 load_values $end
     $var wire 1 1 select_k $end
     $var wire 1 2 enable $end
     $var wire 1 3 clear $end
     $var wire 1 4 load_outputs $end
     $var wire 4 O a00 [3:0] $end
     $var wire 4 P a01 [3:0] $end
     $var wire 4 Q a10 [3:0] $end
     $var wire 4 R a11 [3:0] $end
     $var wire 4 S b00 [3:0] $end
     $var wire 4 T b01 [3:0] $end
     $var wire 4 U b10 [3:0] $end
     $var wire 4 V b11 [3:0] $end
     $var wire 16 , c00 [15:0] $end
     $var wire 16 - c01 [15:0] $end
     $var wire 16 . c10 [15:0] $end
     $var wire 16 / c11 [15:0] $end
     $var wire 4 5 a00_l [3:0] $end
     $var wire 4 6 a01_l [3:0] $end
     $var wire 4 7 a10_l [3:0] $end
     $var wire 4 8 a11_l [3:0] $end
     $var wire 4 9 b00_l [3:0] $end
     $var wire 4 : b01_l [3:0] $end
     $var wire 4 ; b10_l [3:0] $end
     $var wire 4 < b11_l [3:0] $end
     $var wire 4 = mac_valid [3:0] $end
     $var wire 4 b mac_load [3:0] $end
     $var wire 4 > mac_clear [3:0] $end
     $var wire 4 ? mac_a[3] [3:0] $end
     $var wire 4 @ mac_a[2] [3:0] $end
     $var wire 4 A mac_a[1] [3:0] $end
     $var wire 4 B mac_a[0] [3:0] $end
     $var wire 4 C mac_b[3] [3:0] $end
     $var wire 4 D mac_b[2] [3:0] $end
     $var wire 4 E mac_b[1] [3:0] $end
     $var wire 4 F mac_b[0] [3:0] $end
     $var wire 16 # mac_c00 [15:0] $end
     $var wire 16 $ mac_c01 [15:0] $end
     $var wire 16 % mac_c10 [15:0] $end
     $var wire 16 & mac_c11 [15:0] $end
     $scope module mac_u_0 $end
      $var wire 32 [ ACC_WIDTH [31:0] $end
      $var wire 32 Z D_WIDTH [31:0] $end
      $var wire 1 W clk $end
      $var wire 1 2 valid $end
      $var wire 1 3 clear $end
      $var wire 4 B A [3:0] $end
      $var wire 4 F B [3:0] $end
      $var wire 16 # acc_out [15:0] $end
      $var wire 8 G mult [7:0] $end
      $var wire 16 H mult_extended [15:0] $end
      $var wire 16 ' acc_next [15:0] $end
      $var wire 16 # acc [15:0] $end
     $upscope $end
     $scope module mac_u_1 $end
      $var wire 32 [ ACC_WIDTH [31:0] $end
      $var wire 32 Z D_WIDTH [31:0] $end
      $var wire 1 W clk $end
      $var wire 1 2 valid $end
      $var wire 1 3 clear $end
      $var wire 4 A A [3:0] $end
      $var wire 4 E B [3:0] $end
      $var wire 16 $ acc_out [15:0] $end
      $var wire 8 I mult [7:0] $end
      $var wire 16 J mult_extended [15:0] $end
      $var wire 16 ( acc_next [15:0] $end
      $var wire 16 $ acc [15:0] $end
     $upscope $end
     $scope module mac_u_2 $end
      $var wire 32 [ ACC_WIDTH [31:0] $end
      $var wire 32 Z D_WIDTH [31:0] $end
      $var wire 1 W clk $end
      $var wire 1 2 valid $end
      $var wire 1 3 clear $end
      $var wire 4 @ A [3:0] $end
      $var wire 4 D B [3:0] $end
      $var wire 16 % acc_out [15:0] $end
      $var wire 8 K mult [7:0] $end
      $var wire 16 L mult_extended [15:0] $end
      $var wire 16 ) acc_next [15:0] $end
      $var wire 16 % acc [15:0] $end
     $upscope $end
     $scope module mac_u_3 $end
      $var wire 32 [ ACC_WIDTH [31:0] $end
      $var wire 32 Z D_WIDTH [31:0] $end
      $var wire 1 W clk $end
      $var wire 1 2 valid $end
      $var wire 1 3 clear $end
      $var wire 4 ? A [3:0] $end
      $var wire 4 C B [3:0] $end
      $var wire 16 & acc_out [15:0] $end
      $var wire 8 M mult [7:0] $end
      $var wire 16 N mult_extended [15:0] $end
      $var wire 16 * acc_next [15:0] $end
      $var wire 16 & acc [15:0] $end
     $upscope $end
    $upscope $end
   $upscope $end
  $upscope $end
 $upscope $end
$enddefinitions $end


#0
b000 "
b0000000000000000 #
b0000000000000000 $
b0000000000000000 %
b0000000000000000 &
b0000000000000000 '
b0000000000000000 (
b0000000000000000 )
b0000000000000000 *
1+
b0000000000000000 ,
b0000000000000000 -
b0000000000000000 .
b0000000000000000 /
00
01
02
03
04
b0000 5
b0000 6
b0000 7
b0000 8
b0000 9
b0000 :
b0000 ;
b0000 <
b0000 =
b0000 >
b0000 ?
b0000 @
b0000 A
b0000 B
b0000 C
b0000 D
b0000 E
b0000 F
b00000000 G
b0000000000000000 H
b00000000 I
b0000000000000000 J
b00000000 K
b0000000000000000 L
b00000000 M
b0000000000000000 N
b0001 O
b0010 P
b0011 Q
b0100 R
b0101 S
b0110 T
b0111 U
b1000 V
0W
0X
b000 Y
b00000000000000000000000000000100 Z
b00000000000000000000000000010000 [
b00000000000000000000000000001010 \
b000 ]
b001 ^
b010 _
b011 `
b100 a
b0000 b
#5000
1W
#10000
0W
#15000
1W
#20000
0W
#25000
1W
#30000
0W
1X
b001 Y
#35000
b001 "
0+
10
13
b1111 >
1W
b010 Y
#40000
0W
0X
#45000
b010 "
b0000000000000101 '
b0000000000000110 (
b0000000000001111 )
b0000000000010010 *
00
12
03
b0001 5
b0010 6
b0011 7
b0100 8
b0101 9
b0110 :
b0111 ;
b1000 <
b1111 =
b0000 >
b0011 ?
b0011 @
b0001 A
b0001 B
b0110 C
b0101 D
b0110 E
b0101 F
b00000101 G
b0000000000000101 H
b00000110 I
b0000000000000110 J
b00001111 K
b0000000000001111 L
b00010010 M
b0000000000010010 N
1W
b011 Y
#50000
0W
#55000
b011 "
b0000000000000101 #
b0000000000000110 $
b0000000000001111 %
b0000000000010010 &
b0000000000010011 '
b0000000000010110 (
b0000000000101011 )
b0000000000110010 *
11
b0100 ?
b0100 @
b0010 A
b0010 B
b1000 C
b0111 D
b1000 E
b0111 F
b00001110 G
b0000000000001110 H
b00010000 I
b0000000000010000 J
b00011100 K
b0000000000011100 L
b00100000 M
b0000000000100000 N
1W
b100 Y
#60000
0W
#65000
b100 "
b0000000000010011 #
b0000000000010110 $
b0000000000101011 %
b0000000000110010 &
01
02
14
b0000 =
b0000 ?
b0000 @
b0000 A
b0000 B
b0000 C
b0000 D
b0000 E
b0000 F
b00000000 G
b0000000000000000 H
b00000000 I
b0000000000000000 J
b00000000 K
b0000000000000000 L
b00000000 M
b0000000000000000 N
1W
b000 Y
#70000
0W
#75000
b000 "
1+
b0000000000010011 ,
b0000000000010110 -
b0000000000101011 .
b0000000000110010 /
04
1W
